ansible_filter
