Metadata-Version: 2.1
Name: ansible-filter
Version: 1.0.1
Summary: The filter module for Hetzner
Home-page: https://github.com/nl2go/ansible-filter
Author: Sanan Guliyev
Author-email: sanan.quliyev@gmail.com
Maintainer: Newsletter2Go
Maintainer-email: ops@newsletter2go.com
License: MIT
Project-URL: Issue tracker, https://github.com/nl2go/ansible-filter/issues
Project-URL: Code, https://github.com/nl2go/ansible-filter
Keywords: hetzner ansible filter
Platform: UNKNOWN
Classifier: Programming Language :: Python :: 2
Classifier: Programming Language :: Python :: 2.7
Classifier: Programming Language :: Python :: 3
Classifier: Programming Language :: Python :: 3.6
Classifier: Programming Language :: Python :: 3.7
Classifier: Programming Language :: Python :: 3.8
Classifier: License :: OSI Approved :: MIT License
Classifier: Operating System :: OS Independent
Requires-Python: >=2.7,!=3.0.*,!=3.1.*,!=3.2.*,!=3.3.*,!=3.4.*,!=3.5.*
